Metadata-Version: 1.1
Name: bibtexvcs
Version: 2015.16
Summary: a Python package for managing a BibTeX database and related documents
Home-page: http://github.com/supermihi/bibtevxcs
Author: Michael Helmling
Author-email: michaelhelmling@posteo.de
License: GPL3
Keywords: bibliography bibtex jabref
Platform: UNKNOWN
Classifier: Development Status :: 4 - Beta
Classifier: Intended Audience :: Science/Research
Classifier: License :: OSI Approved :: GNU General Public License v3 or later (GPLv3+)
Classifier: Operating System :: OS Independent
Classifier: Programming Language :: Python :: 2.7
Classifier: Programming Language :: Python :: 3
Classifier: Topic :: Database :: Front-Ends
